CHANGELOG.rst
MANIFEST.in
README.rst
setup.py
src/ua2/__init__.py
src/ua2.otl.egg-info/PKG-INFO
src/ua2.otl.egg-info/SOURCES.txt
src/ua2.otl.egg-info/dependency_links.txt
src/ua2.otl.egg-info/eager_resources.txt
src/ua2.otl.egg-info/namespace_packages.txt
src/ua2.otl.egg-info/not-zip-safe
src/ua2.otl.egg-info/requires.txt
src/ua2.otl.egg-info/top_level.txt
src/ua2/otl/__init__.py
src/ua2/otl/generator.py
src/ua2/otl/urls.py
src/ua2/otl/views.py