Metadata-Version: 1.0
Name: ua2.otl
Version: 0.0.1
Summary: Django one time link generator and processor
Home-page: https://bitbucket.org/ua2crm/ua2.otl
Author: Vic Bukhantsov
Author-email: vic@ua2crm.com
License: BSD License
Platform: UNKNOWN
